<mirrors>
  <mirror>
    <!-- China, Shanghai -->
    <id>redv.com</id>
    <url>http://mirrors.redv.com/maven2</url>
    <mirrorOf>central</mirrorOf>
  </mirror>
  <mirror>
    <!-- Denmark -->
    <id>dotsrc.org</id>
    <url>http://mirrors.dotsrc.org/maven2</url>
    <mirrorOf>central</mirrorOf>
  </mirror>
  <mirror>
    <!-- Denmark -->
    <id>sunsite.dk</id>
    <url>http://mirrors.sunsite.dk/maven2</url>
    <mirrorOf>central</mirrorOf>
  </mirror>
  <mirror>
    <!-- Spain, Sevilla -->
    <id>cica.es</id>
    <url>http://ftp.cica.es/mirrors/maven2</url>
    <mirrorOf>central</mirrorOf>
  </mirror>
  <mirror>
    <!-- United States, North Carolina -->
    <id>ibiblio.org</id>
    <url>http://mirrors.ibiblio.org/pub/mirrors/maven2</url>
    <mirrorOf>central</mirrorOf>
  </mirror>
  <mirror>
    <!-- United States, North Carolina -->
    <id>ibiblio.net</id>
    <url>http://www.ibiblio.net/pub/packages/maven2</url>
    <mirrorOf>central</mirrorOf>
  </mirror>
</mirrors>